luminesce/__init__.py
luminesce/__version__.py
luminesce/api_client.py
luminesce/configuration.py
luminesce/exceptions.py
luminesce/rest.py
luminesce/api/__init__.py
luminesce/api/application_metadata_api.py
luminesce/api/binary_downloading_api.py
luminesce/api/certificate_management_api.py
luminesce/api/current_table_field_catalog_api.py
luminesce/api/health_checking_endpoint_api.py
luminesce/api/historically_executed_queries_api.py
luminesce/api/multi_query_execution_api.py
luminesce/api/sql_background_execution_api.py
luminesce/api/sql_design_api.py
luminesce/api/sql_execution_api.py
luminesce/models/__init__.py
luminesce/models/access_controlled_action.py
luminesce/models/access_controlled_resource.py
luminesce/models/access_controlled_resource_identifier_part_schema_attribute.py
luminesce/models/action_id.py
luminesce/models/aggregate_function.py
luminesce/models/aggregation.py
luminesce/models/auto_detect_type.py
luminesce/models/available_field.py
luminesce/models/available_parameter.py
luminesce/models/background_multi_query_progress_response.py
luminesce/models/background_multi_query_response.py
luminesce/models/background_query_cancel_response.py
luminesce/models/background_query_progress_response.py
luminesce/models/background_query_response.py
luminesce/models/background_query_state.py
luminesce/models/case_statement_design.py
luminesce/models/case_statement_item.py
luminesce/models/certificate_action.py
luminesce/models/certificate_file_type.py
luminesce/models/certificate_state.py
luminesce/models/certificate_status.py
luminesce/models/certificate_type.py
luminesce/models/column.py
luminesce/models/column_info.py
luminesce/models/condition_attributes.py
luminesce/models/convert_to_view_data.py
luminesce/models/cursor_position.py
luminesce/models/data_type.py
luminesce/models/error_highlight_item.py
luminesce/models/error_highlight_request.py
luminesce/models/error_highlight_response.py
luminesce/models/expression_with_alias.py
luminesce_sdk_preview-1.16.765.dist-info/METADATA
luminesce_sdk_preview-1.16.765.dist-info/WHEEL
luminesce_sdk_preview-1.16.765.dist-info/top_level.txt
luminesce_sdk_preview-1.16.765.dist-info/RECORD
