Metadata-Version: 2.1
Name: luminesce-sdk-preview
Version: 1.16.765
Summary: Python Preview SDK for Luminesce API
Home-page: https://github.com/finbourne/luminesce-sdk-python-preview
Author: FINBOURNE Technology
Author-email: engineering@finbourne.com
License: MIT
Keywords: OpenAPI,FINBOURNE,LUSID,Notifications API
Platform: UNKNOWN
Requires-Dist: certifi (>=14.05.14)
Requires-Dist: python-dateutil (>=2.5.3)
Requires-Dist: pytz (>=2019.1)
Requires-Dist: requests (>=2.27.1)
Requires-Dist: six (>=1.10)
Requires-Dist: urllib3 (>=1.26.9)
Requires-Dist: finbourne-sdk-utilities (>=0.0.10)
